contentful_management-2.15.1.dist-info/METADATA
contentful_management-2.15.1.dist-info/WHEEL
contentful_management-2.15.1.dist-info/entry_points.txt
contentful_management-2.15.1.dist-info/licenses/LICENSE
contentful_management/__init__.py
contentful_management/api_key.py
contentful_management/api_keys_proxy.py
contentful_management/array.py
contentful_management/asset.py
contentful_management/assets_proxy.py
contentful_management/client.py
contentful_management/client_proxy.py
contentful_management/content_type.py
contentful_management/content_type_editor_interfaces_proxy.py
contentful_management/content_type_entries_proxy.py
contentful_management/content_type_field.py
contentful_management/content_type_field_types.py
contentful_management/content_type_field_validation.py
contentful_management/content_type_metadata.py
contentful_management/content_type_resource_proxy.py
contentful_management/content_type_snapshots_proxy.py
contentful_management/content_types_proxy.py
contentful_management/editor_interface.py
contentful_management/editor_interfaces_proxy.py
contentful_management/entries_proxy.py
contentful_management/entry.py
contentful_management/entry_resource_proxy.py
contentful_management/entry_snapshots_proxy.py
contentful_management/environment.py
contentful_management/environment_assets_proxy.py
contentful_management/environment_content_types_proxy.py
contentful_management/environment_entries_proxy.py
contentful_management/environment_locales_proxy.py
contentful_management/environment_resource_proxy.py
contentful_management/environment_ui_extensions_proxy.py
contentful_management/environments_proxy.py
contentful_management/errors.py
contentful_management/locale.py
contentful_management/locales_proxy.py
contentful_management/organization.py
contentful_management/organization_periodic_usage.py
contentful_management/organization_periodic_usages_proxy.py
contentful_management/organization_users_proxy.py
contentful_management/organizations_proxy.py
contentful_management/personal_access_token.py
contentful_management/personal_access_tokens_proxy.py
contentful_management/preview_api_key.py
contentful_management/preview_api_keys_proxy.py
contentful_management-2.15.1.dist-info/RECORD
