Metadata-Version: 2.1
Name: contentful_management
Version: 2.15.1
Summary: Contentful Management API Client
Keywords: contentful,management,cma,cms,content
Author-Email: Contentful GmbH <prd-ecosystem-dx@contentful.com>
License: MIT
Classifier: Programming Language :: Python :: 3
Classifier: Programming Language :: Python :: 3.9
Classifier: Programming Language :: Python :: 3.10
Classifier: Programming Language :: Python :: 3.11
Classifier: Programming Language :: Python :: 3.12
Project-URL: Homepage, https://www.contentful.com/
Project-URL: Repository, https://github.com/contentful/contentful-management.py
Project-URL: Documentation, https://www.contentful.com/developers/docs/references/content-management-api/
Project-URL: Changelog, https://github.com/contentful/contentful-management.py/changelog/
Requires-Python: >=3.8
Requires-Dist: requests==2.32.4
Requires-Dist: python-dateutil==2.9.0.post0
Provides-Extra: test
Requires-Dist: vcrpy==6.0.1; extra == "test"
Requires-Dist: tox==4.20.0; extra == "test"
Requires-Dist: coverage; extra == "test"
Provides-Extra: dev
Requires-Dist: flake8; extra == "dev"
Requires-Dist: black; extra == "dev"
Requires-Dist: isort; extra == "dev"
Requires-Dist: sphinx>=7.1.2; extra == "dev"
Requires-Dist: pdm; extra == "dev"
